LICENSE
MANIFEST.in
README.md
setup.cfg
setup.py
jungle/__init__.py
jungle/asg.py
jungle/cli.py
jungle/ec2.py
jungle/elb.py
jungle/emr.py
jungle/rds.py
jungle.egg-info/PKG-INFO
jungle.egg-info/SOURCES.txt
jungle.egg-info/dependency_links.txt
jungle.egg-info/entry_points.txt
jungle.egg-info/not-zip-safe
jungle.egg-info/pbr.json
jungle.egg-info/requires.txt
jungle.egg-info/top_level.txt
requirements/common.txt
requirements/development.txt
requirements/test.txt
tests/.coverage
tests/config
tests/conftest.py
tests/test_asg.py
tests/test_cli.py
tests/test_ec2.py
tests/test_elb.py
tests/test_emr.py
tests/test_rds.py
tests/htmlcov/conftest.html
tests/htmlcov/conftest_py.html
tests/htmlcov/coverage_html.js
tests/htmlcov/index.html
tests/htmlcov/jquery.debounce.min.js
tests/htmlcov/jquery.hotkeys.js
tests/htmlcov/jquery.isonscreen.js
tests/htmlcov/jquery.min.js
tests/htmlcov/jquery.tablesorter.min.js
tests/htmlcov/keybd_closed.png
tests/htmlcov/keybd_open.png
tests/htmlcov/status.dat
tests/htmlcov/status.json
tests/htmlcov/style.css
tests/htmlcov/test_asg_py.html
tests/htmlcov/test_cli.html
tests/htmlcov/test_cli_py.html
tests/htmlcov/test_ec2.html
tests/htmlcov/test_ec2_py.html
tests/htmlcov/test_elb.html
tests/htmlcov/test_elb_py.html
tests/htmlcov/test_emr.html
tests/htmlcov/test_emr_py.html
tests/htmlcov/test_utils.html